pycruisemapper/__init__.py
pycruisemapper/const.py
pycruisemapper/classes/__init__.py
pycruisemapper/classes/api.py
pycruisemapper/classes/cruise.py
pycruisemapper/classes/flag.py
pycruisemapper/classes/http.py
pycruisemapper/classes/location.py
pycruisemapper/classes/ship.py
pycruisemapper/classes/shipline.py
pycruisemapper-0.9.0.dist-info/METADATA
pycruisemapper-0.9.0.dist-info/WHEEL
pycruisemapper-0.9.0.dist-info/licenses/LICENSE
pycruisemapper-0.9.0.dist-info/RECORD
