Metadata-Version: 2.1
Name: pycruisemapper
Version: 0.9.0
Summary: Simple Python script to fetch data from CruiseMapper
Project-URL: Homepage, https://kumig.it/kumitterer/pycruisemapper
Project-URL: Bug Tracker, https://kumig.it/kumitterer/pycruisemapper/issues
Author-email: Kumi Mitterer <pycruisemapper@kumi.email>
License: Copyright (c) 2022 Kumi Mitterer <pycruisemapper@kumi.email>
License-File: LICENSE
Classifier: License :: OSI Approved :: MIT License
Classifier: Operating System :: OS Independent
Classifier: Programming Language :: Python :: 3
Requires-Python: >=3.8
